README.md
setup.py
object_forge/__init__.py
object_forge/creator.py
object_forge/definition.py
object_forge/references.py
object_forge.egg-info/PKG-INFO
object_forge.egg-info/SOURCES.txt
object_forge.egg-info/dependency_links.txt
object_forge.egg-info/top_level.txt
object_forge/yaml/__init__.py
object_forge/yaml/reading.py
object_forge/yaml/writing.py