Metadata-Version: 1.0
Name: object-forge
Version: 0.0.1
Summary: Load objects from yaml file, create objects from definition and assemble them into single application
Home-page: UNKNOWN
Author: Przemysław Kot
Author-email: przemyslaw.kot@gmail.com
License: MIT
Platform: UNKNOWN
